Metadata-Version: 2.1
Name: python-internal-privat
Version: 1.0.1
Summary: This module is designed for quick interaction with the privatbank API.
Home-page: https://gitlab.onix.ua/onix-systems/python-internal-privat
Author: ihor.sotnyk
Author-email: ihor.sotnyk@onix-systems.com
Keywords: files speedfiles
Classifier: Programming Language :: Python :: 3.11
Classifier: License :: OSI Approved :: MIT License
Classifier: Operating System :: OS Independent
Requires-Python: >=3.6
